tree_sitter_jinja/__init__.py
tree_sitter_jinja/__init__.pyi
tree_sitter_jinja/_binding.pyd
tree_sitter_jinja/binding.c
tree_sitter_jinja/py.typed
tree_sitter_jinja/queries/highlights.scm
tree_sitter_jinja/queries/locals.scm
tree_sitter_jinja/queries/tags.scm
tree_sitter_jinja-0.3.3.dist-info/METADATA
tree_sitter_jinja-0.3.3.dist-info/WHEEL
tree_sitter_jinja-0.3.3.dist-info/top_level.txt
tree_sitter_jinja-0.3.3.dist-info/RECORD
